scikit_hep_testdata-0.5.8.dist-info/licenses/LICENSE
skhep_testdata/__init__.py
skhep_testdata/__main__.py
skhep_testdata/local_files.py
skhep_testdata/py.typed
skhep_testdata/remote_datasets.yml
skhep_testdata/remote_files.py
skhep_testdata/version.py
skhep_testdata/data/__init__.py
skhep_testdata/data/file_list.txt
skhep_testdata/data/pyhf-ins1748602-probability-models.doi
skhep_testdata/data/pylhe-testfile-madgraph-2.0.0-wbj.lhe.readme
skhep_testdata/data/pylhe-testfile-madgraph-2.2.1-Z-ckkwl.lhe.gz.readme
skhep_testdata/data/pylhe-testfile-madgraph-2.2.1-Z-fxfx.lhe.gz.readme
skhep_testdata/data/pylhe-testfile-madgraph-2.2.1-Z-mlm.lhe.gz.readme
skhep_testdata/data/pylhe-testfile-pythia-6.413-ttbar.lhe.readme
scikit_hep_testdata-0.5.8.dist-info/METADATA
scikit_hep_testdata-0.5.8.dist-info/WHEEL
scikit_hep_testdata-0.5.8.dist-info/entry_points.txt
scikit_hep_testdata-0.5.8.dist-info/top_level.txt
scikit_hep_testdata-0.5.8.dist-info/zip-safe
scikit_hep_testdata-0.5.8.dist-info/RECORD
