Metadata-Version: 2.4
Name: scikit_hep_testdata
Version: 0.5.8
Summary: Example HEP files for testing and demonstrating
Home-page: https://github.com/scikit-hep/scikit-hep-testdata
Author: Ben Krikler
Author-email: b.krikler@cern.ch
Maintainer: The Scikit-HEP admins
Maintainer-email: scikit-hep-admins@googlegroups.com
License: BSD-3-Clause
Keywords: ROOT,HEP,testing
Classifier: Development Status :: 3 - Alpha
Classifier: Intended Audience :: Developers
Classifier: Natural Language :: English
Classifier: Programming Language :: Python :: 3
Classifier: Programming Language :: Python :: 3 :: Only
Classifier: Programming Language :: Python :: 3.9
Classifier: Programming Language :: Python :: 3.10
Classifier: Programming Language :: Python :: 3.11
Classifier: Programming Language :: Python :: 3.12
Classifier: Programming Language :: Python :: 3.13
Classifier: Programming Language :: Python :: Implementation :: CPython
Classifier: Typing :: Typed
Requires-Python: >=3.9
License-File: LICENSE
Requires-Dist: pyyaml
Requires-Dist: requests
Provides-Extra: test
Requires-Dist: pytest>=6.0.0; extra == "test"
Requires-Dist: pytest-cov; extra == "test"
Dynamic: license-file
